awdflag/__init__.py
awdflag/awdflag.py
core/__init__.py
core/checkPort.py
core/colors.py
core/exception.py
core/getHostName.py
core/logger.py
core/oracle.py
core/psUpload.py
core/smbExec.py
core/smbUpload.py
core/sqlServer.py
core/sshUpload.py
core/winRmExec.py
core/winRmUpload.py
core/wmiExec.py
core/zipObj.py
awdflag-1.2.3.dist-info/LICENSE
awdflag-1.2.3.dist-info/METADATA
awdflag-1.2.3.dist-info/WHEEL
awdflag-1.2.3.dist-info/top_level.txt
awdflag-1.2.3.dist-info/RECORD
